chained/__init__.py
chained/abc_solver.py
chained/functions/__init__.py
chained/functions/lambded.py
chained/type_utils/__init__.py
chained/type_utils/meta.py
chained/type_utils/protocol.py
chained/type_utils/typevar.py
chained-0.0.8.dist-info/LICENCE
chained-0.0.8.dist-info/METADATA
chained-0.0.8.dist-info/WHEEL
chained-0.0.8.dist-info/top_level.txt
chained-0.0.8.dist-info/zip-safe
chained-0.0.8.dist-info/RECORD
